ziqara/__init__.py
ziqara/_response.py
ziqara/client.py
ziqara/resources/__init__.py
ziqara/resources/chat.py
ziqara-0.1.1.dist-info/METADATA
ziqara-0.1.1.dist-info/WHEEL
ziqara-0.1.1.dist-info/top_level.txt
ziqara-0.1.1.dist-info/RECORD
