Metadata-Version: 2.4
Name: ziqara
Version: 0.1.1
Summary: Ziqara Python SDK - Enterprise AI with company knowledge
Author: Ziqara
License: MIT
Project-URL: Homepage, https://ziqara.com
Project-URL: Documentation, https://ziqara.com
Project-URL: Repository, https://github.com/ziqara/ziqara-python
Keywords: ai,rag,enterprise,chat,llm
Classifier: Development Status :: 4 - Beta
Classifier: Intended Audience :: Developers
Classifier: License :: OSI Approved :: MIT License
Classifier: Programming Language :: Python :: 3
Classifier: Programming Language :: Python :: 3.8
Classifier: Programming Language :: Python :: 3.9
Classifier: Programming Language :: Python :: 3.10
Classifier: Programming Language :: Python :: 3.11
Classifier: Programming Language :: Python :: 3.12
Classifier: Topic :: Scientific/Engineering :: Artificial Intelligence
Requires-Python: >=3.8
Requires-Dist: requests>=2.28.0
